big_sqs/__init__.py
big_sqs/big_sqs_client.py
big_sqs-1.1.0.dist-info/LICENSE
big_sqs-1.1.0.dist-info/WHEEL
big_sqs-1.1.0.dist-info/METADATA
big_sqs-1.1.0.dist-info/RECORD
