Metadata-Version: 2.1
Name: big-sqs
Version: 1.1.0
Summary: An SQS client capable of storing oversize message payloads on S3.
Home-page: https://github.com/security-breachlock/big-sqs.git
License: Apache-2.0
Author: Saul Johnson
Author-email: saul.johnson@breachlock.com
Requires-Python: >=3.6,<4.0
Classifier: License :: OSI Approved :: Apache Software License
Classifier: License :: Other/Proprietary License
Classifier: Operating System :: OS Independent
Classifier: Programming Language :: Python :: 3
Classifier: Programming Language :: Python :: 3.10
Classifier: Programming Language :: Python :: 3.6
Classifier: Programming Language :: Python :: 3.7
Classifier: Programming Language :: Python :: 3.8
Classifier: Programming Language :: Python :: 3.9
Requires-Dist: boto3 (==1.22.7)
Project-URL: Repository, https://github.com/security-breachlock/big-sqs.git
